seq_detect/seq_detect.v
//`timescale 1ns / 1ps
//////////////////////////////////////////////////////////////////////////////////
// Company: 
// Engineer: Micah Jeffries
// 
// Create Date: 11/15/2019 03:35:40 PM
// Design Name: 
// Module Name: seq_detect
// Project Name: 
// Target Devices: 
// Tool Versions: 
// Description: FSM that detects two of the following sequences based on a
// btn input: 110010 (btn is asserted), 110110 (btn is not asserted)
// 
// Dependencies: 
// 
// Revision:
// Revision 0.01 - File Created
// Additional Comments:
// 
//////////////////////////////////////////////////////////////////////////////////

module seq_detect(
    input clk,
    input btn,
    input x,
    output reg z
    );
    
    //- next state & present state variables
    reg [2:0] NS;
    //- bit-level state representations
    parameter [2:0] st_A=3'b000, st_B=3'b001, st_C=3'b010, st_D=3'b011;
    parameter [2:0] st_E=3'b100, st_F=3'b101, st_G=3'b110;
    
    //- model the next-state and output decoders      
    always @ (posedge clk)
    begin
    z = 0;// assign all outputs
    case(NS)
        st_A:
        begin
            z = 0;        
            if (x == 1)
                NS = st_B;   
            else
                NS = st_A;
        end
        
        st_B:
        begin
            z = 0;        
            if (x == 1)
                NS = st_C;   
            else
                NS = st_A;
        end
        
        st_C:
        begin
            z = 0;        
            if (x == 1)
                NS = st_C;   
            else
                NS = st_D;
        end
        
        st_D:
        begin
            z = 0;        
            if (x == 1 & btn == 1)
                NS = st_A;
            else if (x == 1 & btn == 0)
                NS = st_E;
            else if (x == 0 & btn == 1)
                NS = st_E;   
            else
                NS = st_A;
        end
        
        st_E:
        begin
            z = 0;        
            if (x == 1)
                NS = st_F;   
            else
                NS = st_A;
        end
        
        st_F:
        begin
            z = 0;        
            if (x == 1)
                NS = st_C;   
            else
                NS = st_G;
        end
        
        st_G:
        begin
            z = 1;        
            if (x == 1)
                NS = st_B;   
            else
                NS = st_A;
        end
           
        default: NS = st_A; 
          
        endcase
    end
    
endmodule

seq_detect/seq_detect_tb.v
`include "seq_detect.v"

module seq_detect_tb;

    reg btn, x, clk = 0;
    wire z;

    always #1 clk = ~clk;

    seq_detect DUT (
        .clk(clk),
        .btn(btn),
        .x(x),
        .z(z)
    ); 

    initial begin
        $dumpon;
        $dumpfile("seq_detect_tb.vcd");
        $dumpvars(0,seq_detect_tb);

        #2;
        btn = 1;
        x = 1; #2; x = 1; #2; x = 0; #2; x = 0; #2; x = 1; #2; x = 0; #2;

        btn = 0;
        x = 1; #2; x = 1; #2; x = 0; #2; x = 1; #2; x = 1; #2; x = 0; #4;

        $finish;
    end

endmodule

seq_detect/seq_detect_tb.vcd
$date
	Sat Nov 05 18:36:41 2022
$end
$version
	Icarus Verilog
$end
$timescale
	1s
$end
$scope module seq_detect_tb $end
$var wire 1 ! z $end
$var reg 1 " btn $end
$var reg 1 # clk $end
$var reg 1 $ x $end
$scope module DUT $end
$var wire 1 % btn $end
$var wire 1 & clk $end
$var wire 1 ' x $end
$var reg 3 ( NS [2:0] $end
$var reg 1 ) z $end
$upscope $end
$upscope $end
$enddefinitions $end
#0
$dumpvars
x)
bx (
x'
0&
x%
x$
0#
x"
x!
$end
#1
b0 (
0)
0!
1#
1&
#2
0#
0&
1$
1'
1"
1%
#3
b1 (
1#
1&
#4
0#
0&
#5
b10 (
1#
1&
#6
0#
0&
0$
0'
#7
b11 (
1#
1&
#8
0#
0&
#9
b100 (
1#
1&
#10
0#
0&
1$
1'
#11
b101 (
1#
1&
#12
0#
0&
0$
0'
#13
b110 (
1#
1&
#14
0#
0&
1$
1'
0"
0%
#15
b1 (
1)
1!
1#
1&
#16
0#
0&
#17
b10 (
0)
0!
1#
1&
#18
0#
0&
0$
0'
#19
b11 (
1#
1&
#20
0#
0&
1$
1'
#21
b100 (
1#
1&
#22
0#
0&
#23
b101 (
1#
1&
#24
0#
0&
0$
0'
#25
b110 (
1#
1&
#26
0#
0&
#27
b0 (
1)
1!
1#
1&
