counter/fsm.v
//FSM that keeps track of the present and next state of the counter
module fsm(reset_n, x_in, clk, NS, PS); 
    input  reset_n, clk;
    input [3:0] x_in; 
    //- next state & present state variables
    output reg [2:0] NS, PS;
    
    //Assign the x_in input as the four synchronous control inputs of the counter
    wire up, even, odd, hold;
    assign up = x_in[0];
    assign even = x_in[1];
    assign odd = x_in[2];
    assign hold = x_in[3];
     
     
    //- bit-level state representations
    parameter [2:0] st_ZERO=3'b000,st_ONE=3'b001,st_TWO=3'b010,st_THREE=3'b011; 
    parameter [2:0] st_FOUR=3'b100,st_FIVE=3'b101,st_SIX=3'b110,st_SEVEN=3'b111;

    //- model the state registers
    always @ (negedge reset_n, posedge clk)
       if (reset_n == 0) 
          PS <= st_ZERO; 
       else
          PS <= NS; 
    
    //- model the next-state
    always @ (up, even, odd, hold, PS)
        begin
        case(PS)
            st_ZERO:
            if (hold == 1'b1)
                NS = st_ZERO;
            else if (even == 1'b0 & up == 1'b1 & hold == 1'b0)
                NS = st_ONE;
            else if (even == 1'b0 & up == 1'b0 & hold == 1'b0)
                NS = st_SEVEN;
            else if (even == 1'b1 & up == 1'b1 & hold == 1'b0)
                NS = st_TWO;
            else if (even == 1'b1 & up == 1'b0 & hold == 1'b0)
                NS = st_SIX;
            st_ONE:
            if (hold == 1'b1)
                NS = st_ONE;
            else if (odd == 1'b0 & up == 1'b1 & hold == 1'b0)
                NS = st_TWO;
            else if (odd == 1'b0 & up == 1'b0 & hold == 1'b0)
                NS = st_ZERO;
            else if (odd == 1'b1 & up == 1'b1 & hold == 1'b0)
                NS = st_THREE;
            else if (odd == 1'b1 & up == 1'b0 & hold == 1'b0)
                NS = st_SEVEN;
            st_TWO:
            if (hold == 1'b1)
                NS = st_TWO;
            else if (even == 1'b0 & up == 1'b1 & hold == 1'b0)
                NS = st_THREE;
            else if (even == 1'b0 & up == 1'b0 & hold == 1'b0)
                NS = st_ONE;
            else if (even == 1'b1 & up == 1'b1 & hold == 1'b0)
                NS = st_FOUR;
            else if (even == 1'b1 & up == 1'b0 & hold == 1'b0)
                NS = st_ZERO;
            st_THREE:
            if (hold == 1'b1)
                NS = st_THREE;
            else if (odd == 1'b0 & up == 1'b1 & hold == 1'b0)
                NS = st_FOUR;
            else if (odd == 1'b0 & up == 1'b0 & hold == 1'b0)
                NS = st_TWO;
            else if (odd == 1'b1 & up == 1'b1 & hold == 1'b0)
                NS = st_FIVE;
            else if (odd == 1'b1 & up == 1'b0 & hold == 1'b0)
                NS = st_ONE;
            st_FOUR:
            if (hold == 1'b1)
                NS = st_FOUR;
            else if (even == 1'b0 & up == 1'b1 & hold == 1'b0)
                NS = st_FIVE;
            else if (even == 1'b0 & up == 1'b0 & hold == 1'b0)
                NS = st_THREE;
            else if (even == 1'b1 & up == 1'b1 & hold == 1'b0)
                NS = st_SIX;
            else if (even == 1'b1 & up == 1'b0 & hold == 1'b0)
                NS = st_TWO;
            st_FIVE:
            if (hold == 1'b1)
                NS = st_FIVE;
            else if (odd == 1'b0 & up == 1'b1 & hold == 1'b0)
                NS = st_SIX;
            else if (odd == 1'b0 & up == 1'b0 & hold == 1'b0)
                NS = st_FOUR;
            else if (odd == 1'b1 & up == 1'b1 & hold == 1'b0)
                NS = st_SEVEN;
            else if (odd == 1'b1 & up == 1'b0 & hold == 1'b0)
                NS = st_THREE;
            st_SIX:
            if (hold == 1'b1)
                NS = st_SIX;
            else if (even == 1'b0 & up == 1'b1 & hold == 1'b0)
                NS = st_SEVEN;
            else if (even == 1'b0 & up == 1'b0 & hold == 1'b0)
                NS = st_FIVE;
            else if (even == 1'b1 & up == 1'b1 & hold == 1'b0)
                NS = st_ZERO;
            else if (even == 1'b1 & up == 1'b0 & hold == 1'b0)
                NS = st_FOUR;
            st_SEVEN:
            if (hold == 1'b1)
                NS = st_SEVEN;
            else if (odd == 1'b0 & up == 1'b1 & hold == 1'b0)
                NS = st_ZERO;
            else if (odd == 1'b0 & up == 1'b0 & hold == 1'b0)
                NS = st_SIX;
            else if (odd == 1'b1 & up == 1'b1 & hold == 1'b0)
                NS = st_ONE;
            else if (odd == 1'b1 & up == 1'b0 & hold == 1'b0)
                NS = st_FIVE;    
            default: NS = st_ZERO; 
            
        endcase
    end              
endmodule

counter/counter_tb.v
`include "fsm.v"

module counter_tb;
    
    reg RESET;
    reg UP;
    reg EVEN;
    reg ODD;
    reg HOLD;
    reg CLK = 0;

    //Set up internal wiring
    wire [2:0] ns, ps;
    wire [3:0] data_in;

    always #1 CLK = ~CLK;

    assign data_in = {HOLD, ODD, EVEN, UP};

    //FSM that keeps track of the present and next state of the counter
    fsm MY_FSM (
        .reset_n (RESET),
        .x_in (data_in),
        .clk (CLK),
        .NS (ns),
        .PS (ps)       );

    initial begin
        $dumpon;
        $dumpfile("counter_tb.vcd");
        $dumpvars(0, counter_tb);

        RESET = 0; UP = 0; EVEN = 0; ODD = 0; HOLD = 0; #5;
        RESET = 1; UP = 1; EVEN = 0; ODD = 0; HOLD = 0; #5;
        RESET = 1; UP = 0; EVEN = 1; ODD = 0; HOLD = 0; #5;
        RESET = 1; UP = 0; EVEN = 0; ODD = 1; HOLD = 0; #5;
        RESET = 1; UP = 0; EVEN = 0; ODD = 0; HOLD = 1; #5;
        $finish;
    end

endmodule

counter/counter_tb.vcd
$date
	Sat Nov 05 17:28:39 2022
$end
$version
	Icarus Verilog
$end
$timescale
	1s
$end
$scope module counter_tb $end
$var wire 4 ! data_in [3:0] $end
$var wire 3 " ns [2:0] $end
$var wire 3 # ps [2:0] $end
$var reg 1 $ CLK $end
$var reg 1 % EVEN $end
$var reg 1 & HOLD $end
$var reg 1 ' ODD $end
$var reg 1 ( RESET $end
$var reg 1 ) UP $end
$scope module MY_FSM $end
$var wire 1 * clk $end
$var wire 1 + even $end
$var wire 1 , hold $end
$var wire 1 - odd $end
$var wire 1 . reset_n $end
$var wire 1 / up $end
$var wire 4 0 x_in [3:0] $end
$var reg 3 1 NS [2:0] $end
$var reg 3 2 PS [2:0] $end
$upscope $end
$upscope $end
$enddefinitions $end
#0
$dumpvars
b0 2
b111 1
b0 0
0/
0.
0-
0,
0+
0*
0)
0(
0'
0&
0%
0$
b0 #
b111 "
b0 !
$end
#1
1$
1*
#2
0$
0*
#3
1$
1*
#4
0$
0*
#5
b111 2
b111 #
b0 1
b0 "
1/
1$
1*
1)
b1 !
b1 0
1(
1.
#6
0$
0*
#7
b1 1
b1 "
b0 2
b0 #
1$
1*
#8
0$
0*
#9
b10 1
b10 "
b1 2
b1 #
1$
1*
#10
b0 1
b0 "
1+
0/
0$
0*
1%
0)
b10 !
b10 0
#11
b110 1
b110 "
b0 2
b0 #
1$
1*
#12
0$
0*
#13
b100 1
b100 "
b110 2
b110 #
1$
1*
#14
0$
0*
#15
b100 2
b100 #
b11 1
b11 "
1-
0+
1$
1*
1'
0%
b100 !
b100 0
#16
0$
0*
#17
b1 1
b1 "
b11 2
b11 #
1$
1*
#18
0$
0*
#19
b111 1
b111 "
b1 2
b1 #
1$
1*
#20
b1 1
b1 "
1,
0-
0$
0*
1&
0'
b1000 !
b1000 0
